Metadata-Version: 2.4
Name: sopel_modules.quotes
Version: 1.2.2
Summary: Sopel Quotes is a module for handling user added IRC quotes
Home-page: http://github.com/rustybower/sopel-quotes
Author: Rusty Bower
Author-email: rusty@rustybower.com
License: MIT License
License-File: LICENSE
Requires-Dist: pymysql
Requires-Dist: sopel
Requires-Dist: sqlalchemy
Dynamic: author
Dynamic: author-email
Dynamic: description
Dynamic: description-content-type
Dynamic: home-page
Dynamic: license
Dynamic: license-file
Dynamic: requires-dist
Dynamic: summary
